{"cidades":[{"cidade":"Crato","bandeira":"http:\/\/www.mbi.com.br\/mbi\/files\/media\/image\/brasil-municipio\/ce-crato-bandeira.jpg","estado":"CEARA","estadoabrev":"CE","precomedio":"3.788","combustivel":"Gasolina"},{"cidade":"Juazeiro do Norte","bandeira":"http:\/\/www.mbi.com.br\/mbi\/files\/media\/image\/brasil-municipio\/ce-juazeiro-do-norte-bandeira.jpg","estado":"CEARA","estadoabrev":"CE","precomedio":"3.839","combustivel":"Gasolina"},{"cidade":"Ico","bandeira":"http:\/\/www.mbi.com.br\/mbi\/files\/media\/image\/brasil-municipio\/ce-ico-bandeira.jpg","estado":"CEARA","estadoabrev":"CE","precomedio":"3.891","combustivel":"Gasolina"},{"cidade":"Maracanau","bandeira":"http:\/\/www.mbi.com.br\/mbi\/files\/media\/image\/brasil-municipio\/ce-maracanau-bandeira.jpg","estado":"CEARA","estadoabrev":"CE","precomedio":"3.917","combustivel":"Gasolina"},{"cidade":"Caucaia","bandeira":"http:\/\/www.mbi.com.br\/mbi\/files\/media\/image\/brasil-municipio\/ce-caucaia-bandeira.jpg","estado":"CEARA","estadoabrev":"CE","precomedio":"3.921","combustivel":"Gasolina"},{"cidade":"Iguatu","bandeira":"http:\/\/www.mbi.com.br\/mbi\/files\/media\/image\/brasil-municipio\/ce-iguatu-bandeira.jpg","estado":"CEARA","estadoabrev":"CE","precomedio":"3.941","combustivel":"Gasolina"},{"cidade":"Fortaleza","bandeira":"http:\/\/www.mbi.com.br\/mbi\/files\/media\/image\/brasil-municipio\/ce-fortaleza-bandeira.jpg","estado":"CEARA","estadoabrev":"CE","precomedio":"3.945","combustivel":"Gasolina"},{"cidade":"Beberibe","bandeira":"http:\/\/www.mbi.com.br\/mbi\/files\/media\/image\/brasil-municipio\/xx-ignorado-bandeira.jpg","estado":"CEARA","estadoabrev":"CE","precomedio":"3.982","combustivel":"Gasolina"},{"cidade":"Sobral","bandeira":"http:\/\/www.mbi.com.br\/mbi\/files\/media\/image\/brasil-municipio\/ce-sobral-bandeira.jpg","estado":"CEARA","estadoabrev":"CE","precomedio":"3.983","combustivel":"Gasolina"},{"cidade":"Quixada","bandeira":"http:\/\/www.mbi.com.br\/mbi\/files\/media\/image\/brasil-municipio\/ce-quixada-bandeira.jpg","estado":"CEARA","estadoabrev":"CE","precomedio":"3.984","combustivel":"Gasolina"},{"cidade":"Itapipoca","bandeira":"http:\/\/www.mbi.com.br\/mbi\/files\/media\/image\/brasil-municipio\/ce-itapipoca-bandeira.jpg","estado":"CEARA","estadoabrev":"CE","precomedio":"3.993","combustivel":"Gasolina"},{"cidade":"Crateus","bandeira":"http:\/\/www.mbi.com.br\/mbi\/files\/media\/image\/brasil-municipio\/ce-crateus-bandeira.jpg","estado":"CEARA","estadoabrev":"CE","precomedio":"4.028","combustivel":"Gasolina"},{"cidade":"Limoeiro do Norte","bandeira":"http:\/\/www.mbi.com.br\/mbi\/files\/media\/image\/brasil-municipio\/ce-limoeiro-do-norte-bandeira.jpg","estado":"CEARA","estadoabrev":"CE","precomedio":"4.059","combustivel":"Gasolina"},{"cidade":"Morada Nova","bandeira":"http:\/\/www.mbi.com.br\/mbi\/files\/media\/image\/brasil-municipio\/ce-morada-nova-bandeira.jpg","estado":"CEARA","estadoabrev":"CE","precomedio":"4.075","combustivel":"Gasolina"},{"cidade":"Ipu","bandeira":"http:\/\/www.mbi.com.br\/mbi\/files\/media\/image\/brasil-municipio\/ce-ipu-bandeira.jpg","estado":"CEARA","estadoabrev":"CE","precomedio":"4.106","combustivel":"Gasolina"},{"cidade":"Caninde","bandeira":"http:\/\/www.mbi.com.br\/mbi\/files\/media\/image\/brasil-municipio\/ce-caninde-bandeira.jpg","estado":"CEARA","estadoabrev":"CE","precomedio":"4.184","combustivel":"Gasolina"}]}