{"cidade":{"latitude":"-2,56","longitude":"-44,05","bandeira":"http:\/\/www.mbi.com.br\/mbi\/files\/media\/image\/brasil-municipio\/ma-sao-jose-de-ribamar-bandeira.jpg","cidade":"Sao Jose de Ribamar","estadoabrev":"MA","estado":"MARANHAO","precos":[{"precomedio":"2.944","precomaximos":"3.099","precominimo":"2.829","numpostos":"7","desviopadrao":"0.091","combustivel":"Diesel"},{"precomedio":"3.125","precomaximos":"3.229","precominimo":"3.059","numpostos":"9","desviopadrao":"0.046","combustivel":"Diesel S10"},{"precomedio":"2.984","precomaximos":"3.150","precominimo":"2.799","numpostos":"10","desviopadrao":"0.142","combustivel":"Etanol"},{"precomedio":"3.347","precomaximos":"3.549","precominimo":"3.179","numpostos":"14","desviopadrao":"0.111","combustivel":"Gasolina"}],"quantidade":"14"},"posicao":{"gasolina":7,"etanol":282,"diesel":147,"diesels10":257,"gnv":0}}