{"cidade":{"latitude":"-20,31","longitude":"-40,33","bandeira":"http:\/\/www.mbi.com.br\/mbi\/files\/media\/image\/brasil-municipio\/es-vitoria-bandeira.jpg","cidade":"Vitoria","estadoabrev":"ES","estado":"ESPIRITO SANTO","precos":[{"precomedio":"2.999","precomaximos":"3.090","precominimo":"2.949","numpostos":"16","desviopadrao":"0.036","combustivel":"Diesel"},{"precomedio":"2.191","precomaximos":"2.199","precominimo":"2.180","numpostos":"6","desviopadrao":"0.006","combustivel":"GNV"},{"precomedio":"3.123","precomaximos":"3.200","precominimo":"3.060","numpostos":"17","desviopadrao":"0.039","combustivel":"Diesel S10"},{"precomedio":"3.097","precomaximos":"3.190","precominimo":"2.880","numpostos":"25","desviopadrao":"0.067","combustivel":"Etanol"},{"precomedio":"3.646","precomaximos":"3.750","precominimo":"3.550","numpostos":"30","desviopadrao":"0.054","combustivel":"Gasolina"}],"quantidade":"30"},"posicao":{"gasolina":169,"etanol":332,"diesel":249,"diesels10":255,"gnv":58}}