{"posto":{"logo":"https:\/\/lh3.googleusercontent.com\/-M6pqq5R0NoA\/V6JuGfwPAUI\/AAAAAAAAB3U\/IIcNuoS4gTEJ1maIWwZbk2jpXTueSKSVQCCo\/s300\/riobranco.png","latitude":"-18.1883887","longitude":"-47.9379","cidade":"Catalao","estado":"GOIAS","estadoabrev":"GO","combustivel":"Diesel","razao":"Marli Tavares A Lee - Epp","endereco":"Rua   111 Esquina Com Av Jose Marcelino, S\/n Quadra 32 Lote 11","bairro":"Castelo Branco","hash":"b43f033a4992172b205fb4c447d3e150","bandeira":"RIO BRANCO","precos":[{"combustivel":"Diesel","data":"17\/08\/2016","preco":"3.110"},{"combustivel":"Etanol","data":"17\/08\/2016","preco":"2.599"},{"combustivel":"Gasolina","data":"17\/08\/2016","preco":"3.899"}]}}