{"posto":{"logo":"https:\/\/lh3.googleusercontent.com\/-JKLdtdxEpV4\/V6Jt8geYWMI\/AAAAAAAAB3U\/_rAnU51IqKoXLxFTLESSHiN2TooBokIHwCCo\/s300\/atlantica.png","latitude":"-18.5194645","longitude":"-40.8130576","cidade":"Barra de Sao Francisco","estado":"ESPIRITO SANTO","estadoabrev":"ES","combustivel":"Diesel","razao":"Comsauto - Com\u00c3\u00a9rcio e Servi\u00c3\u00a7os Para Automoveis Ltda","endereco":"Rodovia Es 320 - Barra de S\u00c3\u00a3o Francisco X Ecoporanga, S\/n Km 20,1","bairro":"Vila Paulista","hash":"f6134d7e1140d8e18745083f647aba94","bandeira":"ATL\u00c3\u201aNTICA","precos":[{"combustivel":"Diesel","data":"16\/08\/2016","preco":"2.980"},{"combustivel":"Diesel S10","data":"16\/08\/2016","preco":"3.040"},{"combustivel":"Etanol","data":"16\/08\/2016","preco":"2.890"},{"combustivel":"Gasolina","data":"16\/08\/2016","preco":"3.690"}]}}